Metadata-Version: 2.1
Name: pyupgrader
Version: 2.5.16b2
Summary: Keep your Python code up to date on client machines.
Author: Noah Blaszak
Author-email: technology.misc@gmail.com
Project-URL: Homepage, https://pypi.org/project/pyupgrader
Project-URL: Documentation, https://github.com/Trogiken/PyUpgrader/wiki
Project-URL: Release Notes, https://github.com/Trogiken/PyUpgrader/wiki/Release-Notes
Project-URL: Source, https://github.com/Trogiken/PyUpgrader
Project-URL: Issues, https://github.com/Trogiken/PyUpgrader/issues
Classifier: Programming Language :: Python :: 3.8
Classifier: Programming Language :: Python :: 3.9
Classifier: Programming Language :: Python :: 3.10
Classifier: Development Status :: 4 - Beta
Classifier: Intended Audience :: Developers
Classifier: License :: OSI Approved :: Apache Software License
Classifier: Operating System :: OS Independent
Requires-Python: >=3.8
License-File: LICENSE
Requires-Dist: pyyaml
Requires-Dist: requests
Requires-Dist: responses
Requires-Dist: packaging
Requires-Dist: setuptools
